mambapy/__init__.py
mambapy/jamba.py
mambapy/lm.py
mambapy/mamba.py
mambapy/mamba2.py
mambapy/pscan.py
mambapy/vim.py
mambapy/onnx/__init__.py
mambapy/onnx/mamba_lm_onnx.py
mambapy/onnx/mamba_onnx.py
mambapy/onnx/onnx_convert.py
mambapy/onnx/onnx_usage.py
mambapy-1.1.0.dist-info/LICENSE
mambapy-1.1.0.dist-info/METADATA
mambapy-1.1.0.dist-info/WHEEL
mambapy-1.1.0.dist-info/top_level.txt
mambapy-1.1.0.dist-info/RECORD
