Metadata-Version: 2.1
Name: mambapy
Version: 1.1.0
Summary: A simple and efficient Mamba implementation in pure PyTorch.
Home-page: https://github.com/alxndrTL/mamba.py
Author: Alexandre TL
Author-email: alexandretl3434@gmail.com
Classifier: Programming Language :: Python :: 3
Classifier: License :: OSI Approved :: MIT License
Classifier: Operating System :: OS Independent
Requires-Python: >=3.6
License-File: LICENSE
Requires-Dist: torch
